data/coco_sp/annotations/person_keypoints_val2017.json
demo/inferencer_demo.py
pocketpose/__init__.py
pocketpose/apis.py
pocketpose/registry.py
pocketpose/summarize_models.py
pocketpose/core/__init__.py
pocketpose/core/config.py
pocketpose/core/registry.py
pocketpose/datasets/__init__.py
pocketpose/datasets/base.py
pocketpose/datasets/blazepose.py
pocketpose/datasets/coco.py
pocketpose/datasets/coco_wholebody.py
pocketpose/datasets/h36m.py
pocketpose/datasets/mhp.py
pocketpose/datasets/mpii.py
pocketpose/engine/__init__.py
pocketpose/engine/runners/__init__.py
pocketpose/engine/runners/base.py
pocketpose/engine/runners/mediapipe.py
pocketpose/engine/runners/onnx.py
pocketpose/engine/runners/tflite.py
pocketpose/inferencers/__init__.py
pocketpose/inferencers/image_inferencer.py
pocketpose/inferencers/video_inferencer.py
pocketpose/models/__init__.py
pocketpose/models/configs/bottomup.json
pocketpose/models/configs/single_stage.json
pocketpose/models/configs/topdown_coord_cls.json
pocketpose/models/configs/topdown_heatmap.json
pocketpose/models/configs/topdown_heatmap.py
pocketpose/models/configs/topdown_keypoint.json
pocketpose/models/configs/topdown_keypoint.py
pocketpose/models/configs/detectors/rtmdet.json
pocketpose/models/decoder/__init__.py
pocketpose/models/decoder/base_decoder.py
pocketpose/models/decoder/heatmap.py
pocketpose/models/decoder/heatmap3d.py
pocketpose/models/decoder/movenet.py
pocketpose/models/decoder/posenet.py
pocketpose/models/decoder/simcc.py
pocketpose/models/detectors/__init__.py
pocketpose/models/detectors/rtmdet.py
pocketpose/models/pose_estimators/__init__.py
pocketpose/models/pose_estimators/base.py
pocketpose/models/pose_estimators/mhp.py
pocketpose/models/pose_estimators/posenet.py
pocketpose/models/pose_estimators/rtmo.py
pocketpose/models/pose_estimators/topdown_coord_cls.py
pocketpose/models/pose_estimators/topdown_heatmap.py
pocketpose/models/pose_estimators/topdown_keypoint.py
pocketpose/models/trackers/__init__.py
pocketpose-1.0.0a2.post0.dist-info/LICENSE
pocketpose-1.0.0a2.post0.dist-info/METADATA
pocketpose-1.0.0a2.post0.dist-info/WHEEL
pocketpose-1.0.0a2.post0.dist-info/top_level.txt
pocketpose-1.0.0a2.post0.dist-info/RECORD
