Metadata-Version: 2.1
Name: pocketpose
Version: 1.0.0a2.post0
Summary: An inference library for real-time human pose estimation.
Author-email: Muhammad Saif Ullah Khan <saifkhichi96@gmail.com>
License: Attribution-NonCommercial 4.0 International
Project-URL: Homepage, https://github.com/PocketPose/python-api
Project-URL: Issues, https://github.com/PocketPose/python-api/issues
Project-URL: Documentation, https://pocketpose.github.io/python-api/
Classifier: Programming Language :: Python :: 3
Classifier: Operating System :: OS Independent
Requires-Python: >=3.8
License-File: LICENSE
Requires-Dist: gdown==4.6.0
Requires-Dist: mediapipe
Requires-Dist: numpy
Requires-Dist: onnxruntime
Requires-Dist: opencv-python
Requires-Dist: Pillow
Requires-Dist: tabulate
Requires-Dist: tensorflow
Requires-Dist: tflite
